src/wb_simulator.sv
module wb_simulator #(
    parameter MEM_FILE = "instruction_memory.memh",
    parameter DEPTH = 1024,
    parameter LATENCY = 3
)(
    input  logic        clk,
    input  logic        rst_n,

    input  logic        req,       // asserted for one cycle to start a transaction
    input  logic        we,        // 0=read, 1=write
    input  logic [31:0] addr,
    input  logic [31:0] wdata,

    output logic [31:0] rdata,
    output logic        busy,      // high while operation is in progress
    output logic        valid      // high for one cycle when read completes
);
    // --- memory ---
    logic [31:0] mem [0:DEPTH-1];
    initial $readmemh(MEM_FILE, mem);

    // --- internal state ---
    logic [$clog2(LATENCY+1)-1:0] counter;
    logic pending;
    logic [31:0] addr_reg;

    // --- behavior ---
    always_ff @(posedge clk or negedge rst_n) begin
        if (!rst_n) begin
            counter <= '0;
            pending <= 0;
            busy    <= 0;
            valid   <= 0;
            rdata   <= 0;
        end else begin
            valid <= 0; // default

            if (req && !busy) begin
                // new request
                pending <= 1;
                busy    <= 1;
                counter <= LATENCY - 1;
                addr_reg <= addr;

                if (we)
                    mem[addr[31:2]] <= wdata; // immediate store
            end
            else if (pending) begin
                if (counter == 0) begin
                    pending <= 0;
                    busy    <= 0;
                    if (!we) begin
                        rdata <= mem[addr_reg[31:2]];
                        valid <= 1; // one-cycle pulse
                    end
                end else begin
                    counter <= counter - 1;
                end
            end
        end
    end
endmodule

src/cache1.sv
module cache1 (
    input  logic clk,
    input  logic rst,

    // Scheduler outputs
    input  logic freeze1,             // do not increment instructions     
    input  logic freeze2,             // do not increment instructions 
    input  logic dependency_on_ins2,  // only time we slide by 1
    

    // Outputs to scheduler
    output logic nothing_filled,          // high when cache is empty (stall)
    output logic [31:0] instruction0,    // current instruction
    output logic [31:0] instruction1    // next instruction
);
    logic [31:0] ins [0:11];
    logic [31:0] n_ins [0:5];
    logic [31:0] past_n_ins [0:5];
    logic busy;
    //logic [2:0] counter;
   //logic [2:0] n_counter;
    logic second_half_cache_to_fill;
    logic [31:0] next_PC;
    logic [31:0] PC;
    //CAVEAT PC UPDATE IS JANK
    always_comb begin
    if (rst)
        next_PC = 32'h0000_0000;
    else if ((n_ins[0] == ins[0] && n_ins[1] == ins[1] && n_ins[2] == ins[2] && n_ins[3] == ins[3] && n_ins[4] == ins[4] && n_ins[5] == ins[5]))
        next_PC = PC + 32'd6;
    else if (freeze1 || freeze2)
        next_PC = PC;
    else if (dependency_on_ins2)
        next_PC = PC + 32'd4;
    else if (!nothing_filled || busy == 1'b1)
        next_PC = PC + 32'd8;
    else 
        next_PC = PC;
    end

    always_ff @(posedge clk) begin
        PC <= next_PC;
    end

    // logic [31:0] n_instruction_0;
    // logic [31:0] n_instruction_1;
    // logic [31:0] n_lookahead_0;
    // logic [31:0] n_lookahead_1;
    // logic [31:0] n_lookahead_2;
    // logic [31:0] n_lookahead_3;

    // --- WB instruction memory simulators ---
    wb_simulator #(
        .MEM_FILE("instruction_memory.memh"),
        .DEPTH(1024),
        .LATENCY(3)
    ) wb_inst0 (
        .clk(clk),
        .rst_n(~rst),
        .req(1'b1),
        .we(1'b0),
        .addr(PC),
        .wdata(32'd0),
        .rdata(n_ins[0]),
        .busy(busy),
        .valid()
    );

    wb_simulator #(
        .MEM_FILE("instruction_memory.memh"),
        .DEPTH(1024),
        .LATENCY(3)
    ) wb_inst1 (
        .clk(clk),
        .rst_n(~rst),
        .req(1'b1),
        .we(1'b0),
        .addr(PC + 32'd4),
        .wdata(32'd0),
        .rdata(n_ins[1]),
        .busy(),
        .valid()
    );

    wb_simulator #(
        .MEM_FILE("instruction_memory.memh"),
        .DEPTH(1024),
        .LATENCY(3)
    ) wb_inst2 (
        .clk(clk),
        .rst_n(~rst),
        .req(1'b1),
        .we(1'b0),
        .addr(PC + 32'd8),
        .wdata(32'd0),
        .rdata(n_ins[2]),
        .busy(),
        .valid()
    );

    wb_simulator #(
        .MEM_FILE("instruction_memory.memh"),
        .DEPTH(1024),
        .LATENCY(3)
    ) wb_inst3 (
        .clk(clk),
        .rst_n(~rst),
        .req(1'b1),
        .we(1'b0),
        .addr(PC + 32'd12),
        .wdata(32'd0),
        .rdata(n_ins[3]),
        .busy(),
        .valid()
    );

    wb_simulator #(
        .MEM_FILE("instruction_memory.memh"),
        .DEPTH(1024),
        .LATENCY(3)
    ) wb_inst4 (
        .clk(clk),
        .rst_n(~rst),
        .req(1'b1),
        .we(1'b0),
        .addr(PC + 32'd16),
        .wdata(32'd0),
        .rdata(n_ins[4]),
        .busy(),
        .valid()
    );

    wb_simulator #(
        .MEM_FILE("instruction_memory.memh"),
        .DEPTH(1024),
        .LATENCY(3)
    ) wb_inst5 (
        .clk(clk),
        .rst_n(~rst),
        .req(1'b1),
        .we(1'b0),
        .addr(PC + 32'd20),
        .wdata(32'd0),
        .rdata(n_ins[5]),
        .busy(),
        .valid()
    );

    always_ff @(posedge clk or posedge rst) begin
    if (rst) begin
        for (int i = 0; i < 6; i++) begin
            past_n_ins[i] <= 32'd0;
        end
        // instruction0 <= 32'd0;
        // instruction1 <= 32'd0;
        for (int i = 0; i < 12; i++) begin
            ins[i] <= 32'd0;
        end
    end 
    else begin
        for (int i = 0; i < 6; i++) begin
            past_n_ins[i] <= n_ins[i];
        end
        // instruction0 <= ins[0];
        // instruction1 <= ins[1];

        if (nothing_filled) begin
            ins[0] <= n_ins[0];
            ins[1] <= n_ins[1];
            ins[2] <= n_ins[2];
            ins[3] <= n_ins[3];
            ins[4] <= n_ins[4];
            ins[5] <= n_ins[5];
        end  
        else if (!freeze1) begin
            // --- Immediate reaction to dependency_on_ins2 ---
            if (dependency_on_ins2) begin
                // Slide by 1 instruction (ins[1] becomes new ins[0])
                ins[0] <= ins[1];
                ins[1] <= ins[2];
                ins[2] <= ins[3];
                ins[3] <= ins[4];
                ins[4] <= ins[5];
                ins[5] <= ins[6];
                ins[6] <= (second_half_cache_to_fill ? n_ins[0] : ins[7]);
                ins[7] <= (second_half_cache_to_fill ? n_ins[1] : ins[8]);
                ins[8] <= (second_half_cache_to_fill ? n_ins[2] : ins[9]);
                ins[9] <= (second_half_cache_to_fill ? n_ins[3] : ins[10]);
                ins[10] <= (second_half_cache_to_fill ? n_ins[4] : ins[11]);
                ins[11] <= (second_half_cache_to_fill ? n_ins[5] : 32'd0);
            end 
            else begin
                // Normal slide by 2 instructions
                ins[0] <= ins[2];
                ins[1] <= ins[3];
                ins[2] <= ins[4];
                ins[3] <= ins[5];
                ins[4] <= ins[6];
                ins[5] <= ins[7];
                ins[6] <= (second_half_cache_to_fill ? n_ins[0] : ins[8]);
                ins[7] <= (second_half_cache_to_fill ? n_ins[1] : ins[9]);
                ins[8] <= (second_half_cache_to_fill ? n_ins[2] : ins[10]);
                ins[9] <= (second_half_cache_to_fill ? n_ins[3] : ins[11]);
                ins[10] <= (second_half_cache_to_fill ? n_ins[4] : 32'd0);
                ins[11] <= (second_half_cache_to_fill ? n_ins[5] : 32'd0);
            end
        end
        else begin
            if (second_half_cache_to_fill) begin
                ins[6] <= n_ins[0];
                ins[7] <= n_ins[1];
                ins[8] <= n_ins[2];
                ins[9] <= n_ins[3];
                ins[10] <= n_ins[4];
                ins[11] <= n_ins[5];
            end
        end
    end
end

assign instruction0 = ins[0]; //nothing_filled ? n_ins[0] : ins[0];
assign instruction1 = ins[1]; //nothing_filled ? n_ins[1] : ins[1];

    always_comb begin
        nothing_filled = (ins[0] == 32'd0 ? 1'b1 : 1'b0);
        // if (counter < 3'd6) begin
        //     n_counter = counter + 3'd1;
        // end
        // else begin
        //     n_counter = counter;
        // end
        second_half_cache_to_fill = 32'd0;
    end
endmodule

testbench/cache1_tb.sv
`timescale 1ns/1ps

module cache1_tb;

  // Clock and reset
  logic clk;
  logic rst;

  // Inputs to DUT
  logic freeze1;
  logic freeze2;
  logic dependency_on_ins2;

  // Outputs from DUT
  logic nothing_filled;
  logic [31:0] instruction0;
  logic [31:0] instruction1;

  // DUT instance
  cache1 dut (
    .clk(clk),
    .rst(rst),
    .freeze1(freeze1),
    .freeze2(freeze2),
    .dependency_on_ins2(dependency_on_ins2),
    .nothing_filled(nothing_filled),
    .instruction0(instruction0),
    .instruction1(instruction1)
  );

  // Clock generation: 10ns period
  initial clk = 0;
  always #5 clk = ~clk;

  // PC increments every 2 cycles by 8 bytes (simulate fetch advancing)

  // Test control
  initial begin
    $dumpfile("waves/cache1.vcd");
    $dumpvars(0, cache1_tb);
    $display("=== CACHE AUTO-FILL TEST START ===");

    // Reset
    rst = 1;
    freeze1 = 1;
    freeze2 = 0;
    dependency_on_ins2 = 0;

    #20;
    rst = 0;

    // Let simulation run for a while
    repeat (20) begin
      @(posedge clk);
      // if ($urandom_range(0, 2) == 0) freeze1 = ~freeze1;
      // if ($urandom_range(0, 2) == 0) freeze2 = ~freeze2;
      //if ($urandom_range(0, 4) == 0) dependency_on_ins2 = ~dependency_on_ins2;
      $display("freeze states: freeze1=%b, freeze2=%b, dependency_on_ins2=%b", dut.freeze1, dut.freeze2, dut.dependency_on_ins2);
      $display("[%0t] PC=%h  ins0=%h  ins1=%h  nothing_filled=%b...Second_fill=%b...busy=%b",
               $time, dut.PC, instruction0, instruction1, nothing_filled, dut.second_half_cache_to_fill, dut.busy);
      $write("ins array: ");
      for (int i = 0; i < 12; i++) begin
        $write("%0h ", dut.ins[i]);
      end
      $display(""); // new line
      $write("n_ins array: ");
      for (int i = 0; i < 6; i++) begin
        $write("%0h ", dut.n_ins[i]);
      end
      $display(""); // new line
      $display(""); // new line
    end
    freeze1 = 0;
    repeat (20) begin
      @(posedge clk);
      // if ($urandom_range(0, 2) == 0) freeze1 = ~freeze1;
      // if ($urandom_range(0, 2) == 0) freeze2 = ~freeze2;
      //if ($urandom_range(0, 4) == 0) dependency_on_ins2 = ~dependency_on_ins2;
      $display("freeze states: freeze1=%b, freeze2=%b, dependency_on_ins2=%b", dut.freeze1, dut.freeze2, dut.dependency_on_ins2);
      $display("[%0t] PC=%h  ins0=%h  ins1=%h  nothing_filled=%b...Second_fill=%b...busy=%b",
               $time, dut.PC, instruction0, instruction1, nothing_filled, dut.second_half_cache_to_fill, dut.busy);
      $write("ins array: ");
      for (int i = 0; i < 12; i++) begin
        $write("%0h ", dut.ins[i]);
      end
      $display(""); // new line
      // $display("f = %h", dut.f); // new line
      $write("n_ins array: ");
      for (int i = 0; i < 6; i++) begin
        $write("%0h ", dut.n_ins[i]);
      end
      $display(""); // new line
      $display(""); // new line
    end

    $display("=== CACHE AUTO-FILL TEST DONE ===");
    $finish;
  end

endmodule

waves/cache1.vcd
$date
	Thu Nov 27 18:46:06 2025
$end
$version
	Icarus Verilog
$end
$timescale
	1ps
$end
$scope module cache1_tb $end
$var wire 1 ! nothing_filled $end
$var wire 32 " instruction1 [31:0] $end
$var wire 32 # instruction0 [31:0] $end
$var reg 1 $ clk $end
$var reg 1 % dependency_on_ins2 $end
$var reg 1 & freeze1 $end
$var reg 1 ' freeze2 $end
$var reg 1 ( rst $end
$scope module dut $end
$var wire 1 $ clk $end
$var wire 1 % dependency_on_ins2 $end
$var wire 1 & freeze1 $end
$var wire 1 ' freeze2 $end
$var wire 32 ) instruction0 [31:0] $end
$var wire 32 * instruction1 [31:0] $end
$var wire 1 ( rst $end
$var wire 1 + busy $end
$var reg 32 , PC [31:0] $end
$var reg 32 - next_PC [31:0] $end
$var reg 1 ! nothing_filled $end
$var reg 1 . second_half_cache_to_fill $end
$scope module wb_inst0 $end
$var wire 32 / addr [31:0] $end
$var wire 1 $ clk $end
$var wire 1 0 req $end
$var wire 1 1 rst_n $end
$var wire 32 2 wdata [31:0] $end
$var wire 1 3 we $end
$var parameter 32 4 DEPTH $end
$var parameter 32 5 LATENCY $end
$var parameter 184 6 MEM_FILE $end
$var reg 32 7 addr_reg [31:0] $end
$var reg 1 + busy $end
$var reg 2 8 counter [1:0] $end
$var reg 1 9 pending $end
$var reg 32 : rdata [31:0] $end
$var reg 1 ; valid $end
$upscope $end
$scope module wb_inst1 $end
$var wire 32 < addr [31:0] $end
$var wire 1 $ clk $end
$var wire 1 = req $end
$var wire 1 > rst_n $end
$var wire 32 ? wdata [31:0] $end
$var wire 1 @ we $end
$var parameter 32 A DEPTH $end
$var parameter 32 B LATENCY $end
$var parameter 184 C MEM_FILE $end
$var reg 32 D addr_reg [31:0] $end
$var reg 1 E busy $end
$var reg 2 F counter [1:0] $end
$var reg 1 G pending $end
$var reg 32 H rdata [31:0] $end
$var reg 1 I valid $end
$upscope $end
$scope module wb_inst2 $end
$var wire 32 J addr [31:0] $end
$var wire 1 $ clk $end
$var wire 1 K req $end
$var wire 1 L rst_n $end
$var wire 32 M wdata [31:0] $end
$var wire 1 N we $end
$var parameter 32 O DEPTH $end
$var parameter 32 P LATENCY $end
$var parameter 184 Q MEM_FILE $end
$var reg 32 R addr_reg [31:0] $end
$var reg 1 S busy $end
$var reg 2 T counter [1:0] $end
$var reg 1 U pending $end
$var reg 32 V rdata [31:0] $end
$var reg 1 W valid $end
$upscope $end
$scope module wb_inst3 $end
$var wire 32 X addr [31:0] $end
$var wire 1 $ clk $end
$var wire 1 Y req $end
$var wire 1 Z rst_n $end
$var wire 32 [ wdata [31:0] $end
$var wire 1 \ we $end
$var parameter 32 ] DEPTH $end
$var parameter 32 ^ LATENCY $end
$var parameter 184 _ MEM_FILE $end
$var reg 32 ` addr_reg [31:0] $end
$var reg 1 a busy $end
$var reg 2 b counter [1:0] $end
$var reg 1 c pending $end
$var reg 32 d rdata [31:0] $end
$var reg 1 e valid $end
$upscope $end
$scope module wb_inst4 $end
$var wire 32 f addr [31:0] $end
$var wire 1 $ clk $end
$var wire 1 g req $end
$var wire 1 h rst_n $end
$var wire 32 i wdata [31:0] $end
$var wire 1 j we $end
$var parameter 32 k DEPTH $end
$var parameter 32 l LATENCY $end
$var parameter 184 m MEM_FILE $end
$var reg 32 n addr_reg [31:0] $end
$var reg 1 o busy $end
$var reg 2 p counter [1:0] $end
$var reg 1 q pending $end
$var reg 32 r rdata [31:0] $end
$var reg 1 s valid $end
$upscope $end
$scope module wb_inst5 $end
$var wire 32 t addr [31:0] $end
$var wire 1 $ clk $end
$var wire 1 u req $end
$var wire 1 v rst_n $end
$var wire 32 w wdata [31:0] $end
$var wire 1 x we $end
$var parameter 32 y DEPTH $end
$var parameter 32 z LATENCY $end
$var parameter 184 { MEM_FILE $end
$var reg 32 | addr_reg [31:0] $end
$var reg 1 } busy $end
$var reg 2 ~ counter [1:0] $end
$var reg 1 !" pending $end
$var reg 32 "" rdata [31:0] $end
$var reg 1 #" valid $end
$upscope $end
$scope begin $ivl_for_loop0 $end
$var integer 32 $" i [31:0] $end
$upscope $end
$scope begin $ivl_for_loop1 $end
$var integer 32 %" i [31:0] $end
$upscope $end
$scope begin $ivl_for_loop2 $end
$var integer 32 &" i [31:0] $end
$upscope $end
$upscope $end
$scope begin $ivl_for_loop4 $end
$var integer 32 '" i [31:0] $end
$upscope $end
$scope begin $ivl_for_loop5 $end
$var integer 32 (" i [31:0] $end
$upscope $end
$scope begin $ivl_for_loop6 $end
$var integer 32 )" i [31:0] $end
$upscope $end
$scope begin $ivl_for_loop7 $end
$var integer 32 *" i [31:0] $end
$upscope $end
$upscope $end
$enddefinitions $end
$comment Show the parameter values. $end
$dumpall
b110100101101110011100110111010001110010011101010110001101110100011010010110111101101110010111110110110101100101011011010110111101110010011110010010111001101101011001010110110101101000 {
b11 z
b10000000000 y
b110100101101110011100110111010001110010011101010110001101110100011010010110111101101110010111110110110101100101011011010110111101110010011110010010111001101101011001010110110101101000 m
b11 l
b10000000000 k
b110100101101110011100110111010001110010011101010110001101110100011010010110111101101110010111110110110101100101011011010110111101110010011110010010111001101101011001010110110101101000 _
b11 ^
b10000000000 ]
b110100101101110011100110111010001110010011101010110001101110100011010010110111101101110010111110110110101100101011011010110111101110010011110010010111001101101011001010110110101101000 Q
b11 P
b10000000000 O
b110100101101110011100110111010001110010011101010110001101110100011010010110111101101110010111110110110101100101011011010110111101110010011110010010111001101101011001010110110101101000 C
b11 B
b10000000000 A
b110100101101110011100110111010001110010011101010110001101110100011010010110111101101110010111110110110101100101011011010110111101110010011110010010111001101101011001010110110101101000 6
b11 5
b10000000000 4
$end
#0
$dumpvars
b0 *"
b0 )"
b0 ("
b0 '"
b0 &"
b1100 %"
b110 $"
0#"
b0 ""
0!"
b0 ~
0}
bx |
0x
b0 w
0v
1u
bx t
0s
b0 r
0q
b0 p
0o
bx n
0j
b0 i
0h
1g
bx f
0e
b0 d
0c
b0 b
0a
bx `
0\
b0 [
0Z
1Y
bx X
0W
b0 V
0U
b0 T
0S
bx R
0N
b0 M
0L
1K
bx J
0I
b0 H
0G
b0 F
0E
bx D
0@
b0 ?
0>
1=
bx <
0;
b0 :
09
b0 8
bx 7
03
b0 2
01
10
bx /
0.
b0 -
bx ,
0+
b0 *
b0 )
1(
0'
1&
0%
0$
b0 #
b0 "
1!
$end
#5000
b100 <
b1000 J
b1100 X
b10000 f
b10100 t
b0 ,
b0 /
b1100 %"
b110 $"
1$
#10000
0$
#15000
b1100 %"
b110 $"
1$
#20000
11
1>
1L
1Z
1h
1v
b110 -
0$
0(
#25000
b1100 -
b0 7
b10 8
1+
19
b100 D
b10 F
1E
1G
b1000 R
b10 T
1S
1U
b1100 `
b10 b
1a
1c
b10000 n
b10 p
1o
1q
b10100 |
b10 ~
1}
1!"
b1010 <
b1110 J
b10010 X
b10110 f
b11010 t
b110 ,
b110 /
b110 ("
b1100 '"
b110 &"
1$
#30000
0$
#35000
b10010 -
b1 8
b1 F
b1 T
b1 b
b1 p
b1 ~
b10000 <
b10100 J
b11000 X
b11100 f
b100000 t
b1100 ,
b1100 /
b110 ("
b1100 '"
b110 &"
1$
#40000
0$
#45000
b11000 -
b0 8
b0 F
b0 T
b0 b
b0 p
b0 ~
b10110 <
b11010 J
b11110 X
b100010 f
b100110 t
b10010 ,
b10010 /
b110 ("
b1100 '"
b110 &"
1$
#50000
0$
#55000
1;
b100001000000010010011 :
0+
09
1I
b100001000000010010011 H
0E
0G
1W
b100001000000010010011 V
0S
0U
1e
b100001000000010010011 d
0a
0c
1s
b100001000000010010011 r
0o
0q
1#"
b100001000000010010011 ""
0}
0!"
b11100 <
b100000 J
b100100 X
b101000 f
b101100 t
b11000 ,
b11000 /
b110 ("
b1100 '"
b110 &"
1$
#60000
0$
#65000
0!
b11110 -
b11000 7
b10 8
1+
19
0;
b11100 D
b10 F
1E
1G
0I
b100000 R
b10 T
1S
1U
0W
b100100 `
b10 b
1a
1c
0e
b101000 n
b10 p
1o
1q
0s
b101100 |
b10 ~
1}
1!"
0#"
b100001000000010010011 "
b100001000000010010011 *
b100001000000010010011 #
b100001000000010010011 )
b110 ("
b1100 '"
b110 &"
1$
#70000
0$
#75000
b100100 -
b1 8
b1 F
b1 T
b1 b
b1 p
b1 ~
b100010 <
b100110 J
b101010 X
b101110 f
b110010 t
b11110 ,
b11110 /
b110 ("
b1100 '"
b110 &"
1$
#80000
0$
#85000
b101010 -
b0 8
b0 F
b0 T
b0 b
b0 p
b0 ~
b101000 <
b101100 J
b110000 X
b110100 f
b111000 t
b100100 ,
b100100 /
b110 ("
b1100 '"
b110 &"
1$
#90000
0$
#95000
1;
0+
09
1I
0E
0G
1W
0S
0U
1e
0a
0c
1s
b100010000000100010011 r
0o
0q
1#"
b100010000000100010011 ""
0}
0!"
b101110 <
b110010 J
b110110 X
b111010 f
b111110 t
b101010 ,
b101010 /
b110 ("
b1100 '"
b110 &"
1$
#100000
0$
#105000
b101010 7
b10 8
1+
19
0;
b101110 D
b10 F
1E
1G
0I
b110010 R
b10 T
1S
1U
0W
b110110 `
b10 b
1a
1c
0e
b111010 n
b10 p
1o
1q
0s
b111110 |
b10 ~
1}
1!"
0#"
b110 ("
b1100 '"
b110 &"
1$
#110000
0$
#115000
b1 8
b1 F
b1 T
b1 b
b1 p
b1 ~
b110 ("
b1100 '"
b110 &"
1$
#120000
0$
#125000
b0 8
b0 F
b0 T
b0 b
b0 p
b0 ~
b110 ("
b1100 '"
b110 &"
1$
#130000
0$
#135000
1;
b100010000000100010011 :
0+
09
1I
b100010000000100010011 H
0E
0G
1W
b100010000000100010011 V
0S
0U
1e
b100010000000100010011 d
0a
0c
1s
0o
0q
1#"
0}
0!"
b110 ("
b1100 '"
b110 &"
1$
#140000
0$
#145000
b10 8
1+
19
0;
b10 F
1E
1G
0I
b10 T
1S
1U
0W
b10 b
1a
1c
0e
b10 p
1o
1q
0s
b10 ~
1}
1!"
0#"
b110 ("
b1100 '"
b110 &"
1$
#150000
0$
#155000
b1 8
b1 F
b1 T
b1 b
b1 p
b1 ~
b110 ("
b1100 '"
b110 &"
1$
#160000
0$
#165000
b0 8
b0 F
b0 T
b0 b
b0 p
b0 ~
b110 ("
b1100 '"
b110 &"
1$
#170000
0$
#175000
1;
0+
09
1I
0E
0G
1W
0S
0U
1e
0a
0c
1s
0o
0q
1#"
0}
0!"
b110 ("
b1100 '"
b110 &"
1$
#180000
0$
#185000
b10 8
1+
19
0;
b10 F
1E
1G
0I
b10 T
1S
1U
0W
b10 b
1a
1c
0e
b10 p
1o
1q
0s
b10 ~
1}
1!"
0#"
b110 ("
b1100 '"
b110 &"
1$
#190000
0$
#195000
b1 8
b1 F
b1 T
b1 b
b1 p
b1 ~
b110 ("
b1100 '"
b110 &"
1$
#200000
0$
#205000
b0 8
b0 F
b0 T
b0 b
b0 p
b0 ~
b110 ("
b1100 '"
b110 &"
1$
#210000
0$
#215000
1;
0+
09
1I
0E
0G
1W
0S
0U
1e
0a
0c
1s
0o
0q
1#"
0}
0!"
b110010 -
0&
b110 ("
b1100 '"
b110 &"
1$
#220000
0$
#225000
b111010 -
b10 8
1+
19
0;
b10 F
1E
1G
0I
b10 T
1S
1U
0W
b10 b
1a
1c
0e
b10 p
1o
1q
0s
b10 ~
1}
1!"
0#"
b110110 <
b111010 J
b111110 X
b1000010 f
b1000110 t
b110010 ,
b110010 /
b110 *"
b1100 )"
b110 &"
1$
#230000
0$
#235000
b1000010 -
b1 8
b1 F
b1 T
b1 b
b1 p
b1 ~
b111110 <
b1000010 J
b1000110 X
b1001010 f
b1001110 t
b111010 ,
b111010 /
b110 *"
b1100 )"
b110 &"
1$
#240000
0$
#245000
1!
b1001010 -
b0 8
b0 F
b0 T
b0 b
b0 p
b0 ~
b1000110 <
b1001010 J
b1001110 X
b1010010 f
b1010110 t
b1000010 ,
b1000010 /
b0 "
b0 *
b0 #
b0 )
b110 *"
b1100 )"
b110 &"
1$
#250000
0$
#255000
0!
b1010000 -
1;
0+
09
1I
0E
0G
1W
0S
0U
1e
0a
0c
1s
0o
0q
1#"
0}
0!"
b1001110 <
b1010010 J
b1010110 X
b1011010 f
b1011110 t
b1001010 ,
b1001010 /
b100010000000100010011 "
b100010000000100010011 *
b100010000000100010011 #
b100010000000100010011 )
b110 *"
b1100 )"
b110 &"
1$
#260000
0$
#265000
b1011000 -
b1001010 7
b10 8
1+
19
0;
b1001110 D
b10 F
1E
1G
0I
b1010010 R
b10 T
1S
1U
0W
b1010110 `
b10 b
1a
1c
0e
b1011010 n
b10 p
1o
1q
0s
b1011110 |
b10 ~
1}
1!"
0#"
b1010100 <
b1011000 J
b1011100 X
b1100000 f
b1100100 t
b1010000 ,
b1010000 /
b110 *"
b1100 )"
b110 &"
1$
#270000
0$
#275000
b1100000 -
b1 8
b1 F
b1 T
b1 b
b1 p
b1 ~
b1011100 <
b1100000 J
b1100100 X
b1101000 f
b1101100 t
b1011000 ,
b1011000 /
b110 *"
b1100 )"
b110 &"
1$
#280000
0$
#285000
1!
b1101000 -
b0 8
b0 F
b0 T
b0 b
b0 p
b0 ~
b1100100 <
b1101000 J
b1101100 X
b1110000 f
b1110100 t
b1100000 ,
b1100000 /
b0 "
b0 *
b0 #
b0 )
b110 *"
b1100 )"
b110 &"
1$
#290000
0$
#295000
b1110000 -
0!
1;
bx :
0+
09
1I
bx H
0E
0G
1W
bx V
0S
0U
1e
bx d
0a
0c
1s
bx r
0o
0q
1#"
bx ""
0}
0!"
b1101100 <
b1110000 J
b1110100 X
b1111000 f
b1111100 t
b1101000 ,
b1101000 /
b100010000000100010011 "
b100010000000100010011 *
b100010000000100010011 #
b100010000000100010011 )
b110 *"
b1100 )"
b110 &"
1$
#300000
0$
#305000
b1111000 -
b1101000 7
b10 8
1+
19
0;
b1101100 D
b10 F
1E
1G
0I
b1110000 R
b10 T
1S
1U
0W
b1110100 `
b10 b
1a
1c
0e
b1111000 n
b10 p
1o
1q
0s
b1111100 |
b10 ~
1}
1!"
0#"
b1110100 <
b1111000 J
b1111100 X
b10000000 f
b10000100 t
b1110000 ,
b1110000 /
b110 *"
b1100 )"
b110 &"
1$
#310000
0$
#315000
b10000000 -
b1 8
b1 F
b1 T
b1 b
b1 p
b1 ~
b1111100 <
b10000000 J
b10000100 X
b10001000 f
b10001100 t
b1111000 ,
b1111000 /
b110 *"
b1100 )"
b110 &"
1$
#320000
0$
#325000
1!
b10001000 -
b0 8
b0 F
b0 T
b0 b
b0 p
b0 ~
b10000100 <
b10001000 J
b10001100 X
b10010000 f
b10010100 t
b10000000 ,
b10000000 /
b0 "
b0 *
b0 #
b0 )
b110 *"
b1100 )"
b110 &"
1$
#330000
0$
#335000
x!
1;
0+
09
1I
0E
0G
1W
0S
0U
1e
0a
0c
1s
0o
0q
1#"
0}
0!"
b10001100 <
b10010000 J
b10010100 X
b10011000 f
b10011100 t
b10001000 ,
b10001000 /
bx "
bx *
bx #
bx )
b110 *"
b1100 )"
b110 &"
1$
#340000
0$
#345000
b10010000 -
b10001000 7
b10 8
1+
19
0;
b10001100 D
b10 F
1E
1G
0I
b10010000 R
b10 T
1S
1U
0W
b10010100 `
b10 b
1a
1c
0e
b10011000 n
b10 p
1o
1q
0s
b10011100 |
b10 ~
1}
1!"
0#"
b110 *"
b1100 )"
b110 &"
1$
#350000
0$
#355000
b10011000 -
b1 8
b1 F
b1 T
b1 b
b1 p
b1 ~
b10010100 <
b10011000 J
b10011100 X
b10100000 f
b10100100 t
b10010000 ,
b10010000 /
b110 *"
b1100 )"
b110 &"
1$
#360000
0$
#365000
1!
b10100000 -
b0 8
b0 F
b0 T
b0 b
b0 p
b0 ~
b10011100 <
b10100000 J
b10100100 X
b10101000 f
b10101100 t
b10011000 ,
b10011000 /
b0 "
b0 *
b0 #
b0 )
b110 *"
b1100 )"
b110 &"
1$
#370000
0$
#375000
x!
1;
0+
09
1I
0E
0G
1W
0S
0U
1e
0a
0c
1s
0o
0q
1#"
0}
0!"
b10100100 <
b10101000 J
b10101100 X
b10110000 f
b10110100 t
b10100000 ,
b10100000 /
bx "
bx *
bx #
bx )
b110 *"
b1100 )"
b110 &"
1$
#380000
0$
#385000
b10101000 -
b10100000 7
b10 8
1+
19
0;
b10100100 D
b10 F
1E
1G
0I
b10101000 R
b10 T
1S
1U
0W
b10101100 `
b10 b
1a
1c
0e
b10110000 n
b10 p
1o
1q
0s
b10110100 |
b10 ~
1}
1!"
0#"
b110 *"
b1100 )"
b110 &"
1$
#390000
0$
#395000
b10110000 -
b1 8
b1 F
b1 T
b1 b
b1 p
b1 ~
b10101100 <
b10110000 J
b10110100 X
b10111000 f
b10111100 t
b10101000 ,
b10101000 /
b110 *"
b1100 )"
b110 &"
1$
#400000
0$
#405000
1!
b10111000 -
b0 8
b0 F
b0 T
b0 b
b0 p
b0 ~
b10110100 <
b10111000 J
b10111100 X
b11000000 f
b11000100 t
b10110000 ,
b10110000 /
b0 "
b0 *
b0 #
b0 )
b110 *"
b1100 )"
b110 &"
1$
#410000
0$
#415000
x!
1;
0+
09
1I
0E
0G
1W
0S
0U
1e
0a
0c
1s
0o
0q
1#"
0}
0!"
b10111100 <
b11000000 J
b11000100 X
b11001000 f
b11001100 t
b10111000 ,
b10111000 /
bx "
bx *
bx #
bx )
b110 *"
b1100 )"
b110 &"
1$
