src/wb_simulator.sv
module wb_simulator #(
    parameter MEM_FILE = "instruction_memory.memh",
    parameter DEPTH = 1024,
    parameter LATENCY = 3
)(
    input  logic        clk,
    input  logic        rst_n,

    input  logic        req,       // asserted for one cycle to start a transaction
    input  logic        we,        // 0=read, 1=write
    input  logic [31:0] addr,
    input  logic [31:0] wdata,

    output logic [31:0] rdata,
    output logic        busy,      // high while operation is in progress
    output logic        valid      // high for one cycle when read completes
);
    // --- memory ---
    logic [31:0] mem [0:DEPTH-1];
    initial $readmemh(MEM_FILE, mem);

    // --- internal state ---
    logic [$clog2(LATENCY+1)-1:0] counter;
    logic pending;
    logic [31:0] addr_reg;

    // --- behavior ---
    always_ff @(posedge clk or negedge rst_n) begin
        if (!rst_n) begin
            counter <= '0;
            pending <= 0;
            busy    <= 0;
            valid   <= 0;
            rdata   <= 0;
        end else begin
            valid <= 0; // default

            if (req && !busy) begin
                // new request
                pending <= 1;
                busy    <= 1;
                counter <= LATENCY - 1;
                addr_reg <= addr;

                if (we)
                    mem[addr[31:2]] <= wdata; // immediate store
            end
            else if (pending) begin
                if (counter == 0) begin
                    pending <= 0;
                    busy    <= 0;
                    if (!we) begin
                        rdata <= mem[addr_reg[31:2]];
                        valid <= 1; // one-cycle pulse
                    end
                end else begin
                    counter <= counter - 1;
                end
            end
        end
    end
endmodule

src/cache1.sv
module cache1 (
    input  logic clk,
    input  logic n_rst,

    // Scheduler outputs
    input  logic freeze1,             // do not increment instructions     
    input  logic freeze2,             // do not increment instructions 
    input  logic dependency_on_ins2,  // only time we slide by 1
    

    // Outputs to scheduler
    output logic nothing_filled,          // high when cache is empty (stall)
    output logic [31:0] instruction0,    // current instruction
    output logic [31:0] instruction1    // next instruction
);
    logic [31:0] ins [0:11];
    logic [31:0] n_ins [0:5];
    logic [31:0] past_n_ins [0:5];
    logic busy;
    //logic [2:0] counter;
   //logic [2:0] n_counter;
    logic second_half_cache_to_fill;
    logic [31:0] next_PC;
    logic [31:0] PC;
    //CAVEAT PC UPDATE IS JANK
    always_comb begin
    if (~n_rst)
        next_PC = 32'h0000_0000;
    else if ((n_ins[0] == ins[0] && n_ins[1] == ins[1] && n_ins[2] == ins[2] && n_ins[3] == ins[3] && n_ins[4] == ins[4] && n_ins[5] == ins[5]))
        next_PC = PC + 32'd6;
    else if (freeze1 || freeze2)
        next_PC = PC;
    else if (dependency_on_ins2)
        next_PC = PC + 32'd4;
    else if (!nothing_filled || busy == 1'b1)
        next_PC = PC + 32'd8;
    else 
        next_PC = PC;
    end

    always_ff @(posedge clk) begin
        PC <= next_PC;
    end

    // logic [31:0] n_instruction_0;
    // logic [31:0] n_instruction_1;
    // logic [31:0] n_lookahead_0;
    // logic [31:0] n_lookahead_1;
    // logic [31:0] n_lookahead_2;
    // logic [31:0] n_lookahead_3;

    // --- WB instruction memory simulators ---
    wb_simulator #(
        .MEM_FILE("instruction_memory.memh"),
        .DEPTH(1024),
        .LATENCY(3)
    ) wb_inst0 (
        .clk(clk),
        .rst_n(~n_rst),
        .req(1'b1),
        .we(1'b0),
        .addr(PC),
        .wdata(32'd0),
        .rdata(n_ins[0]),
        .busy(busy),
        .valid()
    );

    wb_simulator #(
        .MEM_FILE("instruction_memory.memh"),
        .DEPTH(1024),
        .LATENCY(3)
    ) wb_inst1 (
        .clk(clk),
        .rst_n(~n_rst),
        .req(1'b1),
        .we(1'b0),
        .addr(PC + 32'd4),
        .wdata(32'd0),
        .rdata(n_ins[1]),
        .busy(),
        .valid()
    );

    wb_simulator #(
        .MEM_FILE("instruction_memory.memh"),
        .DEPTH(1024),
        .LATENCY(3)
    ) wb_inst2 (
        .clk(clk),
        .rst_n(~n_rst),
        .req(1'b1),
        .we(1'b0),
        .addr(PC + 32'd8),
        .wdata(32'd0),
        .rdata(n_ins[2]),
        .busy(),
        .valid()
    );

    wb_simulator #(
        .MEM_FILE("instruction_memory.memh"),
        .DEPTH(1024),
        .LATENCY(3)
    ) wb_inst3 (
        .clk(clk),
        .rst_n(~n_rst),
        .req(1'b1),
        .we(1'b0),
        .addr(PC + 32'd12),
        .wdata(32'd0),
        .rdata(n_ins[3]),
        .busy(),
        .valid()
    );

    wb_simulator #(
        .MEM_FILE("instruction_memory.memh"),
        .DEPTH(1024),
        .LATENCY(3)
    ) wb_inst4 (
        .clk(clk),
        .rst_n(~n_rst),
        .req(1'b1),
        .we(1'b0),
        .addr(PC + 32'd16),
        .wdata(32'd0),
        .rdata(n_ins[4]),
        .busy(),
        .valid()
    );

    wb_simulator #(
        .MEM_FILE("instruction_memory.memh"),
        .DEPTH(1024),
        .LATENCY(3)
    ) wb_inst5 (
        .clk(clk),
        .rst_n(~n_rst),
        .req(1'b1),
        .we(1'b0),
        .addr(PC + 32'd20),
        .wdata(32'd0),
        .rdata(n_ins[5]),
        .busy(),
        .valid()
    );

    always_ff @(posedge clk or negedge n_rst) begin
    if (~n_rst) begin
        for (int i = 0; i < 6; i++) begin
            past_n_ins[i] <= 32'd0;
        end
        // instruction0 <= 32'd0;
        // instruction1 <= 32'd0;
        for (int i = 0; i < 12; i++) begin
            ins[i] <= 32'd0;
        end
    end 
    else begin
        for (int i = 0; i < 6; i++) begin
            past_n_ins[i] <= n_ins[i];
        end
        // instruction0 <= ins[0];
        // instruction1 <= ins[1];

        if (nothing_filled) begin
            ins[0] <= n_ins[0];
            ins[1] <= n_ins[1];
            ins[2] <= n_ins[2];
            ins[3] <= n_ins[3];
            ins[4] <= n_ins[4];
            ins[5] <= n_ins[5];
        end  
        else if (!freeze1) begin
            // --- Immediate reaction to dependency_on_ins2 ---
            if (dependency_on_ins2) begin
                // Slide by 1 instruction (ins[1] becomes new ins[0])
                ins[0] <= ins[1];
                ins[1] <= ins[2];
                ins[2] <= ins[3];
                ins[3] <= ins[4];
                ins[4] <= ins[5];
                ins[5] <= ins[6];
                ins[6] <= (second_half_cache_to_fill ? n_ins[0] : ins[7]);
                ins[7] <= (second_half_cache_to_fill ? n_ins[1] : ins[8]);
                ins[8] <= (second_half_cache_to_fill ? n_ins[2] : ins[9]);
                ins[9] <= (second_half_cache_to_fill ? n_ins[3] : ins[10]);
                ins[10] <= (second_half_cache_to_fill ? n_ins[4] : ins[11]);
                ins[11] <= (second_half_cache_to_fill ? n_ins[5] : 32'd0);
            end 
            else begin
                // Normal slide by 2 instructions
                ins[0] <= ins[2];
                ins[1] <= ins[3];
                ins[2] <= ins[4];
                ins[3] <= ins[5];
                ins[4] <= ins[6];
                ins[5] <= ins[7];
                ins[6] <= (second_half_cache_to_fill ? n_ins[0] : ins[8]);
                ins[7] <= (second_half_cache_to_fill ? n_ins[1] : ins[9]);
                ins[8] <= (second_half_cache_to_fill ? n_ins[2] : ins[10]);
                ins[9] <= (second_half_cache_to_fill ? n_ins[3] : ins[11]);
                ins[10] <= (second_half_cache_to_fill ? n_ins[4] : 32'd0);
                ins[11] <= (second_half_cache_to_fill ? n_ins[5] : 32'd0);
            end
        end
        else begin
            if (second_half_cache_to_fill) begin
                ins[6] <= n_ins[0];
                ins[7] <= n_ins[1];
                ins[8] <= n_ins[2];
                ins[9] <= n_ins[3];
                ins[10] <= n_ins[4];
                ins[11] <= n_ins[5];
            end
        end
    end
end

assign instruction0 = ins[0]; //nothing_filled ? n_ins[0] : ins[0];
assign instruction1 = ins[1]; //nothing_filled ? n_ins[1] : ins[1];

    always_comb begin
        nothing_filled = (ins[0] == 32'd0 ? 1'b1 : 1'b0);
        // if (counter < 3'd6) begin
        //     n_counter = counter + 3'd1;
        // end
        // else begin
        //     n_counter = counter;
        // end
        second_half_cache_to_fill = 32'd0;
    end
endmodule

testbench/cache1_tb.sv
`timescale 1ns/1ps

module cache1_tb;

  // Clock and reset
  logic clk;
  logic rst;

  // Inputs to DUT
  logic freeze1;
  logic freeze2;
  logic dependency_on_ins2;

  // Outputs from DUT
  logic nothing_filled;
  logic [31:0] instruction0;
  logic [31:0] instruction1;

  // DUT instance
  cache1 dut (
    .clk(clk),
    .n_rst(rst),
    .freeze1(freeze1),
    .freeze2(freeze2),
    .dependency_on_ins2(dependency_on_ins2),
    .nothing_filled(nothing_filled),
    .instruction0(instruction0),
    .instruction1(instruction1)
  );

  // Clock generation: 10ns period
  initial clk = 0;
  always #5 clk = ~clk;

  // PC increments every 2 cycles by 8 bytes (simulate fetch advancing)

  // Test control
  initial begin
    $dumpfile("waves/cache1.vcd");
    $dumpvars(0, cache1_tb);
    $display("=== CACHE AUTO-FILL TEST START ===");

    // Reset
    rst = 0;
    freeze1 = 0;
    freeze2 = 0;
    dependency_on_ins2 = 0;

    #20;
    rst = 1;

    // Let simulation run for a while
    repeat (20) begin
      @(posedge clk);
      // if ($urandom_range(0, 2) == 0) freeze1 = ~freeze1;
      // if ($urandom_range(0, 2) == 0) freeze2 = ~freeze2;
      //if ($urandom_range(0, 4) == 0) dependency_on_ins2 = ~dependency_on_ins2;
      $display("freeze states: freeze1=%b, freeze2=%b, dependency_on_ins2=%b", dut.freeze1, dut.freeze2, dut.dependency_on_ins2);
      $display("[%0t] PC=%h  ins0=%h  ins1=%h  nothing_filled=%b...Second_fill=%b...busy=%b",
               $time, dut.PC, instruction0, instruction1, nothing_filled, dut.second_half_cache_to_fill, dut.busy);
      $write("ins array: ");
      for (int i = 0; i < 12; i++) begin
        $write("%0h ", dut.ins[i]);
      end
      $display(""); // new line
      $write("n_ins array: ");
      for (int i = 0; i < 6; i++) begin
        $write("%0h ", dut.n_ins[i]);
      end
      $display(""); // new line
      $display(""); // new line
    end
    freeze1 = 0;
    repeat (20) begin
      @(posedge clk);
      // if ($urandom_range(0, 2) == 0) freeze1 = ~freeze1;
      // if ($urandom_range(0, 2) == 0) freeze2 = ~freeze2;
      //if ($urandom_range(0, 4) == 0) dependency_on_ins2 = ~dependency_on_ins2;
      $display("freeze states: freeze1=%b, freeze2=%b, dependency_on_ins2=%b", dut.freeze1, dut.freeze2, dut.dependency_on_ins2);
      $display("[%0t] PC=%h  ins0=%h  ins1=%h  nothing_filled=%b...Second_fill=%b...busy=%b",
               $time, dut.PC, instruction0, instruction1, nothing_filled, dut.second_half_cache_to_fill, dut.busy);
      $write("ins array: ");
      for (int i = 0; i < 12; i++) begin
        $write("%0h ", dut.ins[i]);
      end
      $display(""); // new line
      // $display("f = %h", dut.f); // new line
      $write("n_ins array: ");
      for (int i = 0; i < 6; i++) begin
        $write("%0h ", dut.n_ins[i]);
      end
      $display(""); // new line
      $display(""); // new line
    end

    $display("=== CACHE AUTO-FILL TEST DONE ===");
    $finish;
  end

endmodule

waves/cache1.vcd
$date
	Fri Nov 28 19:46:24 2025
$end
$version
	Icarus Verilog
$end
$timescale
	1ps
$end
$scope module cache1_tb $end
$var wire 1 ! nothing_filled $end
$var wire 32 " instruction1 [31:0] $end
$var wire 32 # instruction0 [31:0] $end
$var reg 1 $ clk $end
$var reg 1 % dependency_on_ins2 $end
$var reg 1 & freeze1 $end
$var reg 1 ' freeze2 $end
$var reg 1 ( rst $end
$scope module dut $end
$var wire 1 $ clk $end
$var wire 1 % dependency_on_ins2 $end
$var wire 1 & freeze1 $end
$var wire 1 ' freeze2 $end
$var wire 32 ) instruction0 [31:0] $end
$var wire 32 * instruction1 [31:0] $end
$var wire 1 ( n_rst $end
$var wire 1 + busy $end
$var reg 32 , PC [31:0] $end
$var reg 32 - next_PC [31:0] $end
$var reg 1 ! nothing_filled $end
$var reg 1 . second_half_cache_to_fill $end
$scope module wb_inst0 $end
$var wire 32 / addr [31:0] $end
$var wire 1 $ clk $end
$var wire 1 0 req $end
$var wire 1 ( rst_n $end
$var wire 32 1 wdata [31:0] $end
$var wire 1 2 we $end
$var reg 32 3 addr_reg [31:0] $end
$var reg 1 + busy $end
$var reg 2 4 counter [1:0] $end
$var reg 1 5 pending $end
$var reg 32 6 rdata [31:0] $end
$var reg 1 7 valid $end
$upscope $end
$scope module wb_inst1 $end
$var wire 32 8 addr [31:0] $end
$var wire 1 $ clk $end
$var wire 1 9 req $end
$var wire 1 ( rst_n $end
$var wire 32 : wdata [31:0] $end
$var wire 1 ; we $end
$var reg 32 < addr_reg [31:0] $end
$var reg 1 = busy $end
$var reg 2 > counter [1:0] $end
$var reg 1 ? pending $end
$var reg 32 @ rdata [31:0] $end
$var reg 1 A valid $end
$upscope $end
$scope module wb_inst2 $end
$var wire 32 B addr [31:0] $end
$var wire 1 $ clk $end
$var wire 1 C req $end
$var wire 1 ( rst_n $end
$var wire 32 D wdata [31:0] $end
$var wire 1 E we $end
$var reg 32 F addr_reg [31:0] $end
$var reg 1 G busy $end
$var reg 2 H counter [1:0] $end
$var reg 1 I pending $end
$var reg 32 J rdata [31:0] $end
$var reg 1 K valid $end
$upscope $end
$scope module wb_inst3 $end
$var wire 32 L addr [31:0] $end
$var wire 1 $ clk $end
$var wire 1 M req $end
$var wire 1 ( rst_n $end
$var wire 32 N wdata [31:0] $end
$var wire 1 O we $end
$var reg 32 P addr_reg [31:0] $end
$var reg 1 Q busy $end
$var reg 2 R counter [1:0] $end
$var reg 1 S pending $end
$var reg 32 T rdata [31:0] $end
$var reg 1 U valid $end
$upscope $end
$scope module wb_inst4 $end
$var wire 32 V addr [31:0] $end
$var wire 1 $ clk $end
$var wire 1 W req $end
$var wire 1 ( rst_n $end
$var wire 32 X wdata [31:0] $end
$var wire 1 Y we $end
$var reg 32 Z addr_reg [31:0] $end
$var reg 1 [ busy $end
$var reg 2 \ counter [1:0] $end
$var reg 1 ] pending $end
$var reg 32 ^ rdata [31:0] $end
$var reg 1 _ valid $end
$upscope $end
$scope module wb_inst5 $end
$var wire 32 ` addr [31:0] $end
$var wire 1 $ clk $end
$var wire 1 a req $end
$var wire 1 ( rst_n $end
$var wire 32 b wdata [31:0] $end
$var wire 1 c we $end
$var reg 32 d addr_reg [31:0] $end
$var reg 1 e busy $end
$var reg 2 f counter [1:0] $end
$var reg 1 g pending $end
$var reg 32 h rdata [31:0] $end
$var reg 1 i valid $end
$upscope $end
$scope begin $ivl_for_loop0 $end
$var integer 32 j i [31:0] $end
$upscope $end
$scope begin $ivl_for_loop1 $end
$var integer 32 k i [31:0] $end
$upscope $end
$scope begin $ivl_for_loop2 $end
$var integer 32 l i [31:0] $end
$upscope $end
$upscope $end
$scope begin $ivl_for_loop4 $end
$var integer 32 m i [31:0] $end
$upscope $end
$scope begin $ivl_for_loop5 $end
$var integer 32 n i [31:0] $end
$upscope $end
$scope begin $ivl_for_loop6 $end
$var integer 32 o i [31:0] $end
$upscope $end
$scope begin $ivl_for_loop7 $end
$var integer 32 p i [31:0] $end
$upscope $end
$upscope $end
$enddefinitions $end
#0
$dumpvars
b0 p
b0 o
b0 n
b0 m
b0 l
b1100 k
b110 j
0i
b0 h
0g
b0 f
0e
bx d
0c
b0 b
1a
bx `
0_
b0 ^
0]
b0 \
0[
bx Z
0Y
b0 X
1W
bx V
0U
b0 T
0S
b0 R
0Q
bx P
0O
b0 N
1M
bx L
0K
b0 J
0I
b0 H
0G
bx F
0E
b0 D
1C
bx B
0A
b0 @
0?
b0 >
0=
bx <
0;
b0 :
19
bx 8
07
b0 6
05
b0 4
bx 3
02
b0 1
10
bx /
0.
b0 -
bx ,
0+
b0 *
b0 )
0(
0'
0&
0%
0$
b0 #
b0 "
1!
$end
#5000
b100 8
b1000 B
b1100 L
b10000 V
b10100 `
b0 ,
b0 /
b1100 k
b110 j
1$
#10000
0$
#15000
b1100 k
b110 j
1$
#20000
b110 -
0$
1(
#25000
b1100 -
b10100 d
b10 f
1e
1g
b10000 Z
b10 \
1[
1]
b1100 P
b10 R
1Q
1S
b1000 F
b10 H
1G
1I
b100 <
b10 >
1=
1?
b0 3
b10 4
1+
15
b1010 8
b1110 B
b10010 L
b10110 V
b11010 `
b110 ,
b110 /
b110 l
b110 n
b1100 m
1$
#30000
0$
#35000
b10010 -
b1 4
b1 >
b1 H
b1 R
b1 \
b1 f
b10000 8
b10100 B
b11000 L
b11100 V
b100000 `
b1100 ,
b1100 /
b110 l
b110 n
b1100 m
1$
#40000
0$
#45000
b11000 -
b0 f
b0 \
b0 R
b0 H
b0 >
b0 4
b10110 8
b11010 B
b11110 L
b100010 V
b100110 `
b10010 ,
b10010 /
b110 l
b110 n
b1100 m
1$
#50000
0$
#55000
17
0+
05
1A
b100001000000010010011 @
0=
0?
1K
b100010000000100010011 J
0G
0I
1U
b100001000000010010011 T
0Q
0S
1_
b100010000000100010011 ^
0[
0]
1i
b100001000000010010011 h
0e
0g
b11100 8
b100000 B
b100100 L
b101000 V
b101100 `
b11000 ,
b11000 /
b110 l
b110 n
b1100 m
1$
#60000
0$
#65000
b11110 -
b100001000000010010011 "
b100001000000010010011 *
b101100 d
b10 f
1e
1g
0i
b101000 Z
b10 \
1[
1]
0_
b100100 P
b10 R
1Q
1S
0U
b100000 F
b10 H
1G
1I
0K
b11100 <
b10 >
1=
1?
0A
b11000 3
b10 4
1+
15
07
b110 l
b110 n
b1100 m
1$
#70000
0$
#75000
b100100 -
b1 4
b1 >
b1 H
b1 R
b1 \
b1 f
b100010 8
b100110 B
b101010 L
b101110 V
b110010 `
b11110 ,
b11110 /
b110 l
b110 n
b1100 m
1$
#80000
0$
#85000
b101010 -
b0 f
b0 \
b0 R
b0 H
b0 >
b0 4
b101000 8
b101100 B
b110000 L
b110100 V
b111000 `
b100100 ,
b100100 /
b110 l
b110 n
b1100 m
1$
#90000
0$
#95000
17
b100010000000100010011 6
0+
05
1A
0=
0?
1K
0G
0I
1U
0Q
0S
1_
0[
0]
1i
0e
0g
b101110 8
b110010 B
b110110 L
b111010 V
b111110 `
b101010 ,
b101010 /
b110 l
b110 n
b1100 m
1$
#100000
0$
#105000
0!
b110000 -
b100010000000100010011 #
b100010000000100010011 )
b111110 d
b10 f
1e
1g
0i
b111010 Z
b10 \
1[
1]
0_
b110110 P
b10 R
1Q
1S
0U
b110010 F
b10 H
1G
1I
0K
b101110 <
b10 >
1=
1?
0A
b101010 3
b10 4
1+
15
07
b110 l
b110 n
b1100 m
1$
#110000
0$
#115000
b111000 -
b1 4
b1 >
b1 H
b1 R
b1 \
b1 f
b110100 8
b111000 B
b111100 L
b1000000 V
b1000100 `
b110000 ,
b110000 /
b110 l
b110 n
b1100 m
1$
#120000
0$
#125000
b1000000 -
b0 f
b0 \
b0 R
b0 H
b0 >
b0 4
b111100 8
b1000000 B
b1000100 L
b1001000 V
b1001100 `
b111000 ,
b111000 /
b110 l
b110 n
b1100 m
1$
#130000
0$
#135000
1!
b1000000 -
b0 "
b0 *
b0 #
b0 )
17
0+
05
1A
0=
0?
1K
0G
0I
1U
0Q
0S
1_
0[
0]
1i
0e
0g
b1000100 8
b1001000 B
b1001100 L
b1010000 V
b1010100 `
b1000000 ,
b1000000 /
b110 l
b110 n
b1100 m
1$
#140000
0$
#145000
0!
b1000110 -
b100001000000010010011 "
b100001000000010010011 *
b100010000000100010011 #
b100010000000100010011 )
b1010100 d
b10 f
1e
1g
0i
b1010000 Z
b10 \
1[
1]
0_
b1001100 P
b10 R
1Q
1S
0U
b1001000 F
b10 H
1G
1I
0K
b1000100 <
b10 >
1=
1?
0A
b1000000 3
b10 4
1+
15
07
b110 l
b110 n
b1100 m
1$
#150000
0$
#155000
b1001110 -
b1 4
b1 >
b1 H
b1 R
b1 \
b1 f
b1001010 8
b1001110 B
b1010010 L
b1010110 V
b1011010 `
b1000110 ,
b1000110 /
b110 l
b110 n
b1100 m
1$
#160000
0$
#165000
b1010110 -
b0 f
b0 \
b0 R
b0 H
b0 >
b0 4
b1010010 8
b1010110 B
b1011010 L
b1011110 V
b1100010 `
b1001110 ,
b1001110 /
b110 l
b110 n
b1100 m
1$
#170000
0$
#175000
1!
b1010110 -
b0 "
b0 *
b0 #
b0 )
17
0+
05
1A
0=
0?
1K
0G
0I
1U
0Q
0S
1_
0[
0]
1i
b100010000000100010011 h
0e
0g
b1011010 8
b1011110 B
b1100010 L
b1100110 V
b1101010 `
b1010110 ,
b1010110 /
b110 l
b110 n
b1100 m
1$
#180000
0$
#185000
0!
b1011100 -
b100001000000010010011 "
b100001000000010010011 *
b100010000000100010011 #
b100010000000100010011 )
b1101010 d
b10 f
1e
1g
0i
b1100110 Z
b10 \
1[
1]
0_
b1100010 P
b10 R
1Q
1S
0U
b1011110 F
b10 H
1G
1I
0K
b1011010 <
b10 >
1=
1?
0A
b1010110 3
b10 4
1+
15
07
b110 l
b110 n
b1100 m
1$
#190000
0$
#195000
b1100100 -
b1 4
b1 >
b1 H
b1 R
b1 \
b1 f
b1100000 8
b1100100 B
b1101000 L
b1101100 V
b1110000 `
b1011100 ,
b1011100 /
b110 l
b110 n
b1100 m
1$
#200000
0$
#205000
b1101100 -
b100010000000100010011 "
b100010000000100010011 *
b0 f
b0 \
b0 R
b0 H
b0 >
b0 4
b1101000 8
b1101100 B
b1110000 L
b1110100 V
b1111000 `
b1100100 ,
b1100100 /
b110 l
b110 n
b1100 m
1$
#210000
0$
#215000
1!
b1101100 -
b0 "
b0 *
b0 #
b0 )
17
0+
05
1A
b100010000000100010011 @
0=
0?
1K
0G
0I
1U
b100010000000100010011 T
0Q
0S
1_
0[
0]
1i
0e
0g
b1110000 8
b1110100 B
b1111000 L
b1111100 V
b10000000 `
b1101100 ,
b1101100 /
b110 l
b110 n
b1100 m
1$
#220000
0$
#225000
0!
b1110010 -
b100010000000100010011 "
b100010000000100010011 *
b100010000000100010011 #
b100010000000100010011 )
b10000000 d
b10 f
1e
1g
0i
b1111100 Z
b10 \
1[
1]
0_
b1111000 P
b10 R
1Q
1S
0U
b1110100 F
b10 H
1G
1I
0K
b1110000 <
b10 >
1=
1?
0A
b1101100 3
b10 4
1+
15
07
b110 l
b110 p
b1100 o
1$
#230000
0$
#235000
b1111010 -
b1 4
b1 >
b1 H
b1 R
b1 \
b1 f
b1110110 8
b1111010 B
b1111110 L
b10000010 V
b10000110 `
b1110010 ,
b1110010 /
b110 l
b110 p
b1100 o
1$
#240000
0$
#245000
b10000010 -
b0 f
b0 \
b0 R
b0 H
b0 >
b0 4
b1111110 8
b10000010 B
b10000110 L
b10001010 V
b10001110 `
b1111010 ,
b1111010 /
b110 l
b110 p
b1100 o
1$
#250000
0$
#255000
1!
b10000010 -
b0 "
b0 *
b0 #
b0 )
17
0+
05
1A
bx @
0=
0?
1K
bx J
0G
0I
1U
bx T
0Q
0S
1_
bx ^
0[
0]
1i
bx h
0e
0g
b10000110 8
b10001010 B
b10001110 L
b10010010 V
b10010110 `
b10000010 ,
b10000010 /
b110 l
b110 p
b1100 o
1$
#260000
0$
#265000
0!
b10001010 -
bx "
bx *
b100010000000100010011 #
b100010000000100010011 )
b10010110 d
b10 f
1e
1g
0i
b10010010 Z
b10 \
1[
1]
0_
b10001110 P
b10 R
1Q
1S
0U
b10001010 F
b10 H
1G
1I
0K
b10000110 <
b10 >
1=
1?
0A
b10000010 3
b10 4
1+
15
07
b110 l
b110 p
b1100 o
1$
#270000
0$
#275000
x!
b10010010 -
bx #
bx )
b1 4
b1 >
b1 H
b1 R
b1 \
b1 f
b10001110 8
b10010010 B
b10010110 L
b10011010 V
b10011110 `
b10001010 ,
b10001010 /
b110 l
b110 p
b1100 o
1$
#280000
0$
#285000
b10011010 -
b0 f
b0 \
b0 R
b0 H
b0 >
b0 4
b10010110 8
b10011010 B
b10011110 L
b10100010 V
b10100110 `
b10010010 ,
b10010010 /
b110 l
b110 p
b1100 o
1$
#290000
0$
#295000
1!
b0 "
b0 *
b0 #
b0 )
17
bx 6
0+
05
1A
0=
0?
1K
0G
0I
1U
0Q
0S
1_
0[
0]
1i
0e
0g
b10011110 8
b10100010 B
b10100110 L
b10101010 V
b10101110 `
b10011010 ,
b10011010 /
b110 l
b110 p
b1100 o
1$
#300000
0$
#305000
x!
b10100010 -
bx "
bx *
bx #
bx )
b10101110 d
b10 f
1e
1g
0i
b10101010 Z
b10 \
1[
1]
0_
b10100110 P
b10 R
1Q
1S
0U
b10100010 F
b10 H
1G
1I
0K
b10011110 <
b10 >
1=
1?
0A
b10011010 3
b10 4
1+
15
07
b110 l
b110 p
b1100 o
1$
#310000
0$
#315000
b10101010 -
b1 4
b1 >
b1 H
b1 R
b1 \
b1 f
b10100110 8
b10101010 B
b10101110 L
b10110010 V
b10110110 `
b10100010 ,
b10100010 /
b110 l
b110 p
b1100 o
1$
#320000
0$
#325000
b10110010 -
b0 f
b0 \
b0 R
b0 H
b0 >
b0 4
b10101110 8
b10110010 B
b10110110 L
b10111010 V
b10111110 `
b10101010 ,
b10101010 /
b110 l
b110 p
b1100 o
1$
#330000
0$
#335000
1!
b0 "
b0 *
b0 #
b0 )
17
0+
05
1A
0=
0?
1K
0G
0I
1U
0Q
0S
1_
0[
0]
1i
0e
0g
b10110110 8
b10111010 B
b10111110 L
b11000010 V
b11000110 `
b10110010 ,
b10110010 /
b110 l
b110 p
b1100 o
1$
#340000
0$
#345000
x!
b10111010 -
bx "
bx *
bx #
bx )
b11000110 d
b10 f
1e
1g
0i
b11000010 Z
b10 \
1[
1]
0_
b10111110 P
b10 R
1Q
1S
0U
b10111010 F
b10 H
1G
1I
0K
b10110110 <
b10 >
1=
1?
0A
b10110010 3
b10 4
1+
15
07
b110 l
b110 p
b1100 o
1$
#350000
0$
#355000
b11000010 -
b1 4
b1 >
b1 H
b1 R
b1 \
b1 f
b10111110 8
b11000010 B
b11000110 L
b11001010 V
b11001110 `
b10111010 ,
b10111010 /
b110 l
b110 p
b1100 o
1$
#360000
0$
#365000
b11001010 -
b0 f
b0 \
b0 R
b0 H
b0 >
b0 4
b11000110 8
b11001010 B
b11001110 L
b11010010 V
b11010110 `
b11000010 ,
b11000010 /
b110 l
b110 p
b1100 o
1$
#370000
0$
#375000
1!
b0 "
b0 *
b0 #
b0 )
17
0+
05
1A
0=
0?
1K
0G
0I
1U
0Q
0S
1_
0[
0]
1i
0e
0g
b11001110 8
b11010010 B
b11010110 L
b11011010 V
b11011110 `
b11001010 ,
b11001010 /
b110 l
b110 p
b1100 o
1$
#380000
0$
#385000
x!
b11010010 -
bx "
bx *
bx #
bx )
b11011110 d
b10 f
1e
1g
0i
b11011010 Z
b10 \
1[
1]
0_
b11010110 P
b10 R
1Q
1S
0U
b11010010 F
b10 H
1G
1I
0K
b11001110 <
b10 >
1=
1?
0A
b11001010 3
b10 4
1+
15
07
b110 l
b110 p
b1100 o
1$
#390000
0$
#395000
b11011010 -
b1 4
b1 >
b1 H
b1 R
b1 \
b1 f
b11010110 8
b11011010 B
b11011110 L
b11100010 V
b11100110 `
b11010010 ,
b11010010 /
b110 l
b110 p
b1100 o
1$
#400000
0$
#405000
b11100010 -
b0 f
b0 \
b0 R
b0 H
b0 >
b0 4
b11011110 8
b11100010 B
b11100110 L
b11101010 V
b11101110 `
b11011010 ,
b11011010 /
b110 l
b110 p
b1100 o
1$
#410000
0$
#415000
1!
b0 "
b0 *
b0 #
b0 )
17
0+
05
1A
0=
0?
1K
0G
0I
1U
0Q
0S
1_
0[
0]
1i
0e
0g
b11100110 8
b11101010 B
b11101110 L
b11110010 V
b11110110 `
b11100010 ,
b11100010 /
b110 l
b110 p
b1100 o
1$
